{
  "business_name": "Mobile Example Account",
  "google_pay_preference": "enabled",
  "merchant_country": "US",
  "merchant_currency": "usd",
  "merchant_id": "acct_1HvTI7Lu5o3P18Zp",
  "meta_pay_signed_container_context": null,
  "order": null,
  "ordered_payment_method_types_and_wallets": [
    "card"
  ],
  "customer": {
    "payment_methods": [PAYMENT_METHODS_HERE],
    "customer_session": {
      "id": "cuss_654321",
      "livemode": false,
      "api_key": "ek_12345",
      "api_key_expiry": 1899787184,
      "customer": "cus_1",
      "components": {
        "mobile_payment_element": {
          "enabled": true,
          "features": {
            "payment_method_save": "enabled",
            "payment_method_remove": "enabled",
            "payment_method_remove_last": "enabled",
            "payment_method_save_allow_redisplay_override": null,
            "payment_method_set_as_default": "enabled"
          }
        },
        "customer_sheet": {
          "enabled": false,
          "features": null
        }
      }
    },
    "default_payment_method": DEFAULT_PAYMENT_METHOD_HERE
  },
  "payment_method_preference": {
    "object": "payment_method_preference",
    "country_code": "US",
    "ordered_payment_method_types": [
      "card"
    ],
    "type": "deferred_intent"
  },
  "payment_method_specs": [
    {
      "async": false,
      "fields": [],
      "type": "card"
    }
  ],
  "paypal_express_config": {
    "client_id": null,
    "paypal_merchant_id": null
  },
  "shipping_address_settings": {
    "autocomplete_allowed": true
  },
  "unactivated_payment_method_types": []
}